yfiles_graphs_for_streamlit/__init__.py
yfiles_graphs_for_streamlit/apply_mappings.py
yfiles_graphs_for_streamlit/data_sanitizer.py
yfiles_graphs_for_streamlit/edge.py
yfiles_graphs_for_streamlit/edge_style.py
yfiles_graphs_for_streamlit/label_style.py
yfiles_graphs_for_streamlit/node.py
yfiles_graphs_for_streamlit/node_style.py
yfiles_graphs_for_streamlit/utils.py
yfiles_graphs_for_streamlit/widget.py
yfiles_graphs_for_streamlit/frontend/dist/index.html
yfiles_graphs_for_streamlit/frontend/dist/assets/index-D4vybPis.js
yfiles_graphs_for_streamlit/graph_importer/__init__.py
yfiles_graphs_for_streamlit/graph_importer/factories.py
yfiles_graphs_for_streamlit/graph_importer/importer.py
yfiles_graphs_for_streamlit/graph_importer/interfaces.py
yfiles_graphs_for_streamlit/layout/__init__.py
yfiles_graphs_for_streamlit/layout/configurations.py
yfiles_graphs_for_streamlit/layout/factories.py
yfiles_graphs_for_streamlit/layout/interfaces.py
yfiles_graphs_for_streamlit/layout/layout.py
yfiles_graphs_for_streamlit-1.3.0.data/data/notices/REDISTRIBUTABLES.md
yfiles_graphs_for_streamlit-1.3.0.data/data/notices/THIRD-PARTY-NOTICES-RUNTIME.json
yfiles_graphs_for_streamlit-1.3.0.data/data/notices/THIRD-PARTY-NOTICES.json
yfiles_graphs_for_streamlit-1.3.0.dist-info/licenses/LICENSE.md
yfiles_graphs_for_streamlit-1.3.0.dist-info/METADATA
yfiles_graphs_for_streamlit-1.3.0.dist-info/WHEEL
yfiles_graphs_for_streamlit-1.3.0.dist-info/top_level.txt
yfiles_graphs_for_streamlit-1.3.0.dist-info/RECORD
