Metadata-Version: 2.4
Name: yfiles_graphs_for_streamlit
Version: 1.3.0
Summary: A diagram visualization component for Streamlit powered by yFiles for HTML
Home-page: https://www.yworks.com/products/yfiles-graphs-for-streamlit
Author: yWorks Support Team
Author-email: yfileshtml@yworks.com
License: See LICENSE.md
Project-URL: Homepage, https://www.yworks.com/products/yfiles-graphs-for-streamlit
Project-URL: License, https://github.com/yWorks/yfiles-graphs-for-streamlit/blob/main/LICENSE.md
Project-URL: Bug Tracker, https://github.com/yWorks/yfiles-graphs-for-streamlit/issues
Project-URL: Documentation, https://github.com/yWorks/yfiles-graphs-for-streamlit/
Keywords: Streamlit,component,yfiles,visualization,graph,diagrams
Classifier: Development Status :: 5 - Production/Stable
Classifier: Intended Audience :: Developers
Classifier: Intended Audience :: Science/Research
Classifier: Intended Audience :: Information Technology
Classifier: Topic :: Multimedia :: Graphics
Requires-Python: >=3.7
License-File: LICENSE.md
Requires-Dist: streamlit>=0.63
Dynamic: author
Dynamic: author-email
Dynamic: classifier
Dynamic: description
Dynamic: description-content-type
Dynamic: home-page
Dynamic: keywords
Dynamic: license
Dynamic: license-file
Dynamic: project-url
Dynamic: requires-dist
Dynamic: requires-python
Dynamic: summary
